ohdsi_cohort_schemas/__init__.py
ohdsi_cohort_schemas/models/__init__.py
ohdsi_cohort_schemas/models/cohort.py
ohdsi_cohort_schemas/models/common.py
ohdsi_cohort_schemas/models/concept_set.py
ohdsi_cohort_schemas/models/criteria.py
ohdsi_cohort_schemas/models/vocabulary.py
ohdsi_cohort_schemas/validation.py
ohdsi_cohort_schemas-0.4.1.dist-info/LICENSE
ohdsi_cohort_schemas-0.4.1.dist-info/METADATA
ohdsi_cohort_schemas-0.4.1.dist-info/WHEEL
ohdsi_cohort_schemas-0.4.1.dist-info/RECORD
