Metadata-Version: 2.3
Name: ohdsi-cohort-schemas
Version: 0.4.1
Summary: Pydantic models for validating OHDSI/Circe cohort definition schemas
License: Apache-2.0
Keywords: ohdsi,cohort,schema,validation,pydantic,circe
Author: Chase Sweeting
Author-email: chassweeting@users.noreply.github.com
Requires-Python: >=3.11,<4.0
Classifier: Development Status :: 3 - Alpha
Classifier: Intended Audience :: Developers
Classifier: Intended Audience :: Healthcare Industry
Classifier: Intended Audience :: Science/Research
Classifier: License :: OSI Approved :: Apache Software License
Classifier: Operating System :: OS Independent
Classifier: Programming Language :: Python :: 3
Classifier: Programming Language :: Python :: 3.11
Classifier: Programming Language :: Python :: 3.12
Classifier: Programming Language :: Python :: 3.13
Classifier: Topic :: Scientific/Engineering :: Medical Science Apps.
Classifier: Topic :: Software Development :: Libraries :: Python Modules
Classifier: Typing :: Typed
Requires-Dist: pydantic (>=2.0.0,<3.0.0)
Requires-Dist: typing-extensions (>=4.7.0,<5.0.0)
Project-URL: Documentation, https://github.com/clsweeting/ohdsi-cohort-schemas
Project-URL: Homepage, https://github.com/clsweeting/ohdsi-cohort-schemas
Project-URL: Repository, https://github.com/clsweeting/ohdsi-cohort-schemas
